CHANGES.rst
LICENSE.txt
README.rst
setup.py
pystunnel/__init__.py
pystunnel/pystunnel.py
pystunnel.egg-info/PKG-INFO
pystunnel.egg-info/SOURCES.txt
pystunnel.egg-info/dependency_links.txt
pystunnel.egg-info/entry_points.txt
pystunnel.egg-info/not-zip-safe
pystunnel.egg-info/requires.txt
pystunnel.egg-info/top_level.txt