Metadata-Version: 1.1
Name: pystunnel
Version: 1.0a1
Summary: Python interface to stunnel
Home-page: http://zerodb.io
Author: ZeroDB Inc.
Author-email: stefan@epy.co.at
License: AGPLv3
Keywords: stunnel ssl tunnel tls
Platform: UNKNOWN
Classifier: Development Status :: 3 - Alpha
Classifier: Intended Audience :: Developers
Classifier: License :: OSI Approved :: GNU Affero General Public License v3
Classifier: Operating System :: MacOS :: MacOS X
Classifier: Operating System :: POSIX
Classifier: Programming Language :: Python :: 2.7
Classifier: Programming Language :: Python :: 3.3
Classifier: Programming Language :: Python :: 3.4
Classifier: Programming Language :: Python :: 3.5
